testrift_server/__init__.py
testrift_server/__main__.py
testrift_server/api_handlers.py
testrift_server/cleanup.py
testrift_server/cli.py
testrift_server/config.py
testrift_server/database.py
testrift_server/handlers.py
testrift_server/models.py
testrift_server/protocol.py
testrift_server/protocol_utils.py
testrift_server/testrift_server.yaml
testrift_server/tr_server.py
testrift_server/utils.py
testrift_server/websocket.py
testrift_server/static/at_syntax.js
testrift_server/static/classifications.css
testrift_server/static/classifications.js
testrift_server/static/msgpack.min.js
testrift_server/static/protocol.js
testrift_server/static/status-badges.css
testrift_server/static/test_case_log.css
testrift_server/static/test_case_log.js
testrift_server/templates/analyzer.html
testrift_server/templates/failures.html
testrift_server/templates/index.html
testrift_server/templates/matrix.html
testrift_server/templates/static_banner.html
testrift_server/templates/test_case_log.html
testrift_server/templates/test_run.html
testrift_server-0.5.0.dist-info/licenses/LICENSE
testrift_server-0.5.0.dist-info/METADATA
testrift_server-0.5.0.dist-info/WHEEL
testrift_server-0.5.0.dist-info/entry_points.txt
testrift_server-0.5.0.dist-info/top_level.txt
testrift_server-0.5.0.dist-info/RECORD
