Metadata-Version: 2.4
Name: testrift-server
Version: 0.5.0
Summary: TestRift real-time test run server: live logs, results storage, and web UI for browsing and analysis.
Author: Andreas Anderberg
License-Expression: Apache-2.0
Project-URL: Repository, https://github.com/testrift/testrift-server
Project-URL: Issues, https://github.com/testrift/testrift-server/issues
Requires-Python: >=3.10
License-File: LICENSE
Requires-Dist: aiohttp>=3.8.0
Requires-Dist: aiofiles>=23.0.0
Requires-Dist: PyYAML>=6.0
Requires-Dist: jinja2>=3.0.0
Requires-Dist: aiosqlite>=0.19.0
Requires-Dist: msgpack>=1.0.0
Dynamic: license-file
